App/SRAM_TCAM/RTL_RegisterTransferLevel/decoder_3_to_8.v
module decoder_3_to_8(
    input [2:0] a,
    output [7:0] y
);
assign y[0]=~a[2] & ~a[1] & ~a[0];
assign y[1]=~a[2] & ~a[1] & a[0];
assign y[2]=~a[2] & a[1] & ~a[0];
assign y[3]=~a[2] & a[1] & a[0];
assign y[4]=a[2] & ~a[1] & ~a[0];
assign y[5]=a[2] & ~a[1] & a[0];
assign y[6]=a[2] & a[1] & ~a[0];
assign y[7]=a[2] & a[1] & a[0];
endmodule
module decoder_3_to_8_with_always(
    input [2:0] a,
    output reg [7:0] y
);
always @(*) begin
    case(a)
        3'b000: y=8'b00000001;
        3'b001: y=8'b00000010;
        3'b010: y=8'b00000100;
        3'b011: y=8'b00001000;
        3'b100: y=8'b00010000;
        3'b101: y=8'b00100000;
        3'b110: y=8'b01000000;
        3'b111: y=8'b10000000;
        default: y=8'b00000000;
    endcase
end
endmodule

Doc/OnTap/ThucHanh/decoder_3_to_8_testbench.v
`timescale 1ps/1ps
module decoder_3_to_8_tb;
reg [2:0]a;
wire [7:0]y;
decoder_3_to_8 ut(
    .a(a),
    .y(y)
);
initial begin
    $dumpfile("decoder_3_to_8_wave.vcd");
    $dumpvars(0,decoder_3_to_8_tb);
end
initial begin
    a=3'b000;
    #10;
    a=3'b001;
    #10;
    a=3'b010;
    #10;
    a=3'b011;
    #10;
    a=3'b100;
    #10;
    a=3'b101;
    #10;
    a=3'b110;
    #10;
    a=3'b111;
    #10;
    $finish;
end
initial begin
    $monitor("time=%0t a=%b y=%b",
                    $time,a,y);
end
endmodule

Doc/OnTap/ThucHanh/decoder_3_to_8_wave.vcd
$date
	Mon Jul  6 20:11:35 2026
$end
$version
	Icarus Verilog
$end
$timescale
	1ps
$end
$scope module decoder_3_to_8_tb $end
$var wire 8 ! y [7:0] $end
$var reg 3 " a [2:0] $end
$scope module ut $end
$var wire 3 # a [2:0] $end
$var wire 8 $ y [7:0] $end
$upscope $end
$upscope $end
$enddefinitions $end
$comment Show the parameter values. $end
$dumpall
$end
#0
$dumpvars
b1 $
b0 #
b0 "
b1 !
$end
#10
b10 !
b10 $
b1 "
b1 #
#20
b100 !
b100 $
b10 "
b10 #
#30
b1000 !
b1000 $
b11 "
b11 #
#40
b10000 !
b10000 $
b100 "
b100 #
#50
b100000 !
b100000 $
b101 "
b101 #
#60
b1000000 !
b1000000 $
b110 "
b110 #
#70
b10000000 !
b10000000 $
b111 "
b111 #
