App/SRAM_TCAM/rtl/fullAdder_boolean.v
module fullAdder(
    input a,
    input b,
    input cin,
    output sum,
    output cout
);
wire ab;
wire acin;
wire bcin;
assign sum= a^b^cin;
assign ab=a&b;
assign acin=a&cin;
assign bcin=b&cin;
assign cout= ab|acin|bcin;
endmodule

App/SRAM_TCAM/TB_TestBench/fullAdder_boolean_testbench.v
`timescale 1ns/1ps
module fullAdder_boolean_tb;
reg a;
reg b;
reg cin;
wire sum;
wire cout;
fullAdder uut(
    .a(a),
    .b(b),
    .cin(cin),
    .sum(sum),
    .cout(cout)
);
initial begin
    $dumpfile("fullAdder_boolean.vcd");
    $dumpvars(0,fullAdder_boolean_tb);
end
initial begin
    a=0;b=0;cin=0;
    #10;
    a=0;b=0;cin=1;
    #10;
    a=0;b=1;cin=0;
    #10;
    a=0;b=1;cin=1;
    #10;
    a=1;b=0;cin=0;
    #10;
    a=1;b=0;cin=1;
    #10;
    a=1;b=1;cin=0;
    #10;
    a=1;b=1;cin=1;
    #10;
    $finish;
end
initial begin
    $monitor("time=%0t a=%b b=%b cin=%b sum=%b cout=%b",
                    $time,a,b,cin,sum,cout);
end
endmodule

Doc/OnTap/ThucHanh/fullAdder_boolean.vcd
$date
	Mon Jul  6 13:36:00 2026
$end
$version
	Icarus Verilog
$end
$timescale
	1ps
$end
$scope module fullAdder_boolean_tb $end
$var wire 1 ! sum $end
$var wire 1 " cout $end
$var reg 1 # a $end
$var reg 1 $ b $end
$var reg 1 % cin $end
$scope module uut $end
$var wire 1 # a $end
$var wire 1 & ab $end
$var wire 1 ' acin $end
$var wire 1 $ b $end
$var wire 1 ( bcin $end
$var wire 1 % cin $end
$var wire 1 " cout $end
$var wire 1 ! sum $end
$upscope $end
$upscope $end
$enddefinitions $end
$comment Show the parameter values. $end
$dumpall
$end
#0
$dumpvars
0(
0'
0&
0%
0$
0#
0"
0!
$end
#10000
1!
1%
#20000
0%
1$
#30000
1"
0!
1(
1%
#40000
0"
1!
0(
0%
0$
1#
#50000
1"
0!
1'
1%
#60000
0'
1&
0%
1$
#70000
1!
1'
1(
1%
