Doc/OnTap/ThucHanh/half_adder.v
module half_adder(
    input a,
    input b,
    output sum,
    output carry
);
assign sum= a ^b;
assign carry=a &b;
endmodule

Doc/OnTap/ThucHanh/full_adder_by_x2_half_adder.v
module full_adder_by_x2_half_adder(
    input a,
    input b,
    input cin,
    output sum,
    output cout
);
wire carry1;
wire carry2;
wire sum1;
half_adder ha1(
    .a(a),
    .b(b),
    .sum(sum1),
    .carry(carry1)
);
half_adder ha2(
    .a(sum1),
    .b(cin),
    .sum(sum),
    .carry(carry2)
);
assign cout= carry1|carry2;
endmodule
//iverilog -o full_adder_by_x2_half_adder half_adder.v full_adder_by_x2_half_
//adder.v full_adder_by_x2_half_adder_testbench.v

Doc/OnTap/ThucHanh/full_adder_by_x2_half_adder_testbench.v
`timescale 1ns/1ps
module full_adder_by_x2_half_adder_tb;
reg a;
reg b;
reg cin;
wire sum;
wire cout;
full_adder_by_x2_half_adder uut(
    .a(a),
    .b(b),
    .cin(cin),
    .sum(sum),
    .cout(cout)
); 
initial begin
    $dumpfile("full_adder_by_x2_half_adder.vcd");
    $dumpvars(0,full_adder_by_x2_half_adder_tb);
end
initial begin
    a=0;b=0;cin=0;
    #10;
    a=0;b=0;cin=1;
    #10;
    a=0;b=1;cin=0;
    #10;                
    a=0;b=1;cin=1;
    #10;
    a=1;b=0;cin=0;
    #10;
    a=1;b=0;cin=1;
    #10;
    a=1;b=1;cin=0;
    #10;
    a=1;b=1;cin=1;
    #10;
    $finish;
end
initial begin
    $monitor("time=%0t a=%b b=%b cin=%b sum=%b cout=%b",
                    $time,a,b,cin,sum,cout);
end
endmodule

Doc/OnTap/ThucHanh/full_adder_by_x2_half_adder.vcd
$date
	Mon Jul  6 14:26:26 2026
$end
$version
	Icarus Verilog
$end
$timescale
	1ps
$end
$scope module full_adder_by_x2_half_adder_tb $end
$var wire 1 ! sum $end
$var wire 1 " cout $end
$var reg 1 # a $end
$var reg 1 $ b $end
$var reg 1 % cin $end
$scope module uut $end
$var wire 1 # a $end
$var wire 1 $ b $end
$var wire 1 % cin $end
$var wire 1 " cout $end
$var wire 1 & sum1 $end
$var wire 1 ! sum $end
$var wire 1 ' carry2 $end
$var wire 1 ( carry1 $end
$scope module ha1 $end
$var wire 1 # a $end
$var wire 1 $ b $end
$var wire 1 ( carry $end
$var wire 1 & sum $end
$upscope $end
$scope module ha2 $end
$var wire 1 & a $end
$var wire 1 % b $end
$var wire 1 ' carry $end
$var wire 1 ! sum $end
$upscope $end
$upscope $end
$upscope $end
$enddefinitions $end
$comment Show the parameter values. $end
$dumpall
$end
#0
$dumpvars
0(
0'
0&
0%
0$
0#
0"
0!
$end
#10000
1!
1%
#20000
1&
0%
1$
#30000
1"
0!
1'
1%
#40000
0"
1!
0'
0%
0$
1#
#50000
1"
0!
1'
1%
#60000
0'
0&
1(
0%
1$
#70000
1!
1%
