Doc/OnTap/ThucHanh/Mach_logic_batky.v
//y= (a&b)|(~c)
module logic_batky(
    input a,
    input b,
    input c,
    output y
);
wire t1;
assign t1= a & b;
assign y= t1 | (~c);
endmodule

Doc/OnTap/ThucHanh/Mach_logic_batky_testbench.v
`timescale 1ns/1ps
module mach_logic_batky_tb;
reg a;
reg b;
reg c;
wire y;
logic_batky uut(
    .a(a),
    .b(b),
    .c(c),
    .y(y)
);
initial begin
    $dumpfile("mach_logic_batky.vcd");
    $dumpvars(0,mach_logic_batky_tb);
end
initial begin
    a=0;b=0;c=0;
    #10;
    a=0;b=0;c=1;
    #10;
    a=0;b=1;c=0;
    #10;
    a=0;b=1;c=1;
    #10;
    a=1;b=0;c=0;
    #10;
    a=1;b=0;c=1;
    #10;
    a=1;b=1;c=0;
    #10;
    a=1;b=1;c=1;
    #10;
    $finish;
end
initial begin
    $monitor("time=%0t a=%b b=%b c=%b y=%b",
                    $time,a,b,c,y);
end
endmodule

Doc/OnTap/ThucHanh/mach_logic_batky.vcd
$date
	Sun Jul  5 14:43:51 2026
$end
$version
	Icarus Verilog
$end
$timescale
	1ps
$end
$scope module mach_logic_batky_tb $end
$var wire 1 ! y $end
$var reg 1 " a $end
$var reg 1 # b $end
$var reg 1 $ c $end
$scope module uut $end
$var wire 1 " a $end
$var wire 1 # b $end
$var wire 1 $ c $end
$var wire 1 % t1 $end
$var wire 1 ! y $end
$upscope $end
$upscope $end
$enddefinitions $end
$comment Show the parameter values. $end
$dumpall
$end
#0
$dumpvars
0%
0$
0#
0"
1!
$end
#10000
0!
1$
#20000
1!
0$
1#
#30000
0!
1$
#40000
1!
0$
0#
1"
#50000
0!
1$
#60000
1!
1%
0$
1#
#70000
1$
