Doc/OnTap/ThucHanh/or_gate.v
module or_gate(
    input a,
    input b,
    output y
);
assign y=a|b;
endmodule

Doc/OnTap/ThucHanh/and_gate.v
module and_gate(
    input a,
    input b,
    output y
);
assign y=a&b;
endmodule

App/SRAM_TCAM/rtl/not_gate.v
module not_gate(
    input a,
    output y
);
assign y= ~a;
endmodule

Doc/OnTap/ThucHanh/multiplexer_MUX_ratio_2_to_1.v
module multiplexer_MUX_ratio_2_to_1(
    input a,
    input b,
    input sel,
    output out
);
//assign out = sel ? b :a ;
//y = (~s & a) | (s & b);
//assign out= (~sel & a) | (sel & b );
wire out1;
not_gate not1(
    .a(sel),
    .y(out1)
);
wire s1,s2;
and_gate and1(
    .a(a),
    .b(out1),
    .y(s1)
);
and_gate and2(
    .a(b),
    .b(sel),
    .y(s2)
);
or_gate or1(
    .a(s1),
    .b(s2),
    .y(out)
);
endmodule

Doc/OnTap/ThucHanh/multiplexer_MUX_ratio_2_to_1_testbench.v
`timescale 1ps/1ps
module multiplexer_MUX_ratio_2_to_1_tb;
reg a;
reg b;
reg sel;
wire out;
multiplexer_MUX_ratio_2_to_1 uut(
    .a(a),
    .b(b),
    .sel(sel),
    .out(out)
);

initial begin
    $dumpfile("multiplexer_MUX_ratio_2_to_1.vcd");
    $dumpvars(0,multiplexer_MUX_ratio_2_to_1_tb);
end
initial begin
    a=0;b=0;sel=0;
    #10;
    a=0;b=0;sel=1;
    #10;
    a=0;b=1;sel=0;
    #10;        
    a=0;b=1;sel=1;
    #10;
    a=1;b=0;sel=0;
    #10;
    a=1;b=0;sel=1;
    #10;
    a=1;b=1;sel=0;
    #10;
    a=1;b=1;sel=1;
    #10;
    $finish;
end
initial begin
    $monitor("time=%0t a=%b b=%b sel=%b out=%b",
                    $time,a,b,sel,out); 
end

endmodule

Doc/OnTap/ThucHanh/multiplexer_MUX_ratio_2_to_1.vcd
$date
	Mon Jul  6 16:34:22 2026
$end
$version
	Icarus Verilog
$end
$timescale
	1ps
$end
$scope module multiplexer_MUX_ratio_2_to_1_tb $end
$var wire 1 ! out $end
$var reg 1 " a $end
$var reg 1 # b $end
$var reg 1 $ sel $end
$scope module uut $end
$var wire 1 " a $end
$var wire 1 # b $end
$var wire 1 $ sel $end
$var wire 1 % s2 $end
$var wire 1 & s1 $end
$var wire 1 ' out1 $end
$var wire 1 ! out $end
$scope module and1 $end
$var wire 1 " a $end
$var wire 1 & y $end
$var wire 1 ' b $end
$upscope $end
$scope module and2 $end
$var wire 1 # a $end
$var wire 1 $ b $end
$var wire 1 % y $end
$upscope $end
$scope module not1 $end
$var wire 1 $ a $end
$var wire 1 ' y $end
$upscope $end
$scope module or1 $end
$var wire 1 & a $end
$var wire 1 % b $end
$var wire 1 ! y $end
$upscope $end
$upscope $end
$upscope $end
$enddefinitions $end
$comment Show the parameter values. $end
$dumpall
$end
#0
$dumpvars
1'
0&
0%
0$
0#
0"
0!
$end
#10
0'
1$
#20
1'
0$
1#
#30
1!
1%
0'
1$
#40
1&
1!
1'
0%
0$
0#
1"
#50
0!
0&
0'
1$
#60
1!
1&
1'
0$
1#
#70
0&
1%
0'
1$
