Doc/OnTap/ThucHanh/or_gate.v
module or_gate(
    input a,
    input b,
    output y
);
assign y=a|b;
endmodule

Doc/OnTap/ThucHanh/and_gate.v
module and_gate(
    input a,
    input b,
    output y
);
assign y=a&b;
endmodule

App/SRAM_TCAM/rtl/not_gate.v
module not_gate(
    input a,
    output y
);
assign y= ~a;
endmodule

App/SRAM_TCAM/RTL_RegisterTransferLevel/multiplexer_MUX_ratio_2_to_1.v
module multiplexer_MUX_ratio_2_to_1(
    input a,
    input b,
    input sel,
    output out
);
//assign out = sel ? b :a ;
//y = (~s & a) | (s & b);
//assign out= (~sel & a) | (sel & b );
wire out1;
not_gate not1(
    .a(sel),
    .y(out1)
);
wire s1,s2;
and_gate and1(
    .a(a),
    .b(out1),
    .y(s1)
);
and_gate and2(
    .a(b),
    .b(sel),
    .y(s2)
);
or_gate or1(
    .a(s1),
    .b(s2),
    .y(out)
);
endmodule
module MUX2(
    input a,
    input b,
    input sel,
    output out
);
//assign out = sel ? b :a ;
//y = (~s & a) | (s & b);
//assign out= (~sel & a) | (sel & b );
wire out1;
not_gate not1(
    .a(sel),
    .y(out1)
);
wire s1,s2;
and_gate and1(
    .a(a),
    .b(out1),
    .y(s1)
);
and_gate and2(
    .a(b),
    .b(sel),
    .y(s2)
);
or_gate or1(
    .a(s1),
    .b(s2),
    .y(out)
);
endmodule

App/SRAM_TCAM/rtl/multiplexer_MUX_ratio_4_to_1.v
module multiplexer_MUX_ratio_4_to_1(
    input a,
    input b,
    input c,
    input d,
    input [1:0] sel,
    output out
);
wire out1,out2;
MUX2 mux1(
    .a(a),
    .b(b),
    .sel(sel[0]),
    .out(out1)
);
MUX2 mux2(
    .a(c),
    .b(d), 
    .sel(sel[0]),
    .out(out2)
);
MUX2 mux3(
    .a(out1),
    .b(out2),
    .sel(sel[1]),
    .out(out)
);
endmodule
module MUX4(
    input a,
    input b,
    input c,
    input d,
    input [1:0] sel,
    output out
);
wire out1,out2;
MUX2 mux1(
    .a(a),
    .b(b),
    .sel(sel[0]),
    .out(out1)
);
MUX2 mux2(
    .a(c),
    .b(d), 
    .sel(sel[0]),
    .out(out2)
);
MUX2 mux3(
    .a(out1),
    .b(out2),
    .sel(sel[1]),
    .out(out)
);
endmodule

Doc/OnTap/ThucHanh/multiplexer_MUX_ratio_4_to_1_testbench.v
`timescale 1ps/1ps
module mutiplexer_MUX_ratio_4_to_1_tb;

reg a, b, c, d;
reg [1:0] sel;
wire out;
multiplexer_MUX_ratio_4_to_1 uut(
    .a(a),
    .b(b),
    .c(c),
    .d(d),
    .sel(sel),
    .out(out)
);
initial begin
    $dumpfile("multiplexer_MUX_ratio_4_to_1.vcd");
    $dumpvars(0,mutiplexer_MUX_ratio_4_to_1_tb);
end
initial begin
    a = 0; b = 0; c = 1; d = 1;

    sel = 2'b00; #10;
    sel = 2'b01; #10;
    sel = 2'b10; #10;
    sel = 2'b11; #10;

    a = 1; b = 0; c = 1; d = 0;

    sel = 2'b00; #10;
    sel = 2'b01; #10;
    sel = 2'b10; #10;
    sel = 2'b11; #10;
    $finish;
end   

initial begin
    $monitor("time=%0t a=%b b=%b c=%b d=%b sel=%b out=%b",
                    $time,a,b,c,d,sel,out);
end
endmodule

Doc/OnTap/ThucHanh/multiplexer_MUX_ratio_4_to_1.vcd
$date
	Mon Jul  6 18:31:02 2026
$end
$version
	Icarus Verilog
$end
$timescale
	1ps
$end
$scope module mutiplexer_MUX_ratio_4_to_1_tb $end
$var wire 1 ! out $end
$var reg 1 " a $end
$var reg 1 # b $end
$var reg 1 $ c $end
$var reg 1 % d $end
$var reg 2 & sel [1:0] $end
$scope module uut $end
$var wire 1 " a $end
$var wire 1 # b $end
$var wire 1 $ c $end
$var wire 1 % d $end
$var wire 2 ' sel [1:0] $end
$var wire 1 ( out2 $end
$var wire 1 ) out1 $end
$var wire 1 ! out $end
$scope module mux1 $end
$var wire 1 " a $end
$var wire 1 # b $end
$var wire 1 * sel $end
$var wire 1 + s2 $end
$var wire 1 , s1 $end
$var wire 1 - out1 $end
$var wire 1 ) out $end
$scope module and1 $end
$var wire 1 " a $end
$var wire 1 , y $end
$var wire 1 - b $end
$upscope $end
$scope module and2 $end
$var wire 1 # a $end
$var wire 1 * b $end
$var wire 1 + y $end
$upscope $end
$scope module not1 $end
$var wire 1 * a $end
$var wire 1 - y $end
$upscope $end
$scope module or1 $end
$var wire 1 , a $end
$var wire 1 + b $end
$var wire 1 ) y $end
$upscope $end
$upscope $end
$scope module mux2 $end
$var wire 1 $ a $end
$var wire 1 % b $end
$var wire 1 . sel $end
$var wire 1 / s2 $end
$var wire 1 0 s1 $end
$var wire 1 1 out1 $end
$var wire 1 ( out $end
$scope module and1 $end
$var wire 1 $ a $end
$var wire 1 0 y $end
$var wire 1 1 b $end
$upscope $end
$scope module and2 $end
$var wire 1 % a $end
$var wire 1 . b $end
$var wire 1 / y $end
$upscope $end
$scope module not1 $end
$var wire 1 . a $end
$var wire 1 1 y $end
$upscope $end
$scope module or1 $end
$var wire 1 0 a $end
$var wire 1 / b $end
$var wire 1 ( y $end
$upscope $end
$upscope $end
$scope module mux3 $end
$var wire 1 ) a $end
$var wire 1 ( b $end
$var wire 1 2 sel $end
$var wire 1 3 s2 $end
$var wire 1 4 s1 $end
$var wire 1 5 out1 $end
$var wire 1 ! out $end
$scope module and1 $end
$var wire 1 ) a $end
$var wire 1 4 y $end
$var wire 1 5 b $end
$upscope $end
$scope module and2 $end
$var wire 1 ( a $end
$var wire 1 2 b $end
$var wire 1 3 y $end
$upscope $end
$scope module not1 $end
$var wire 1 2 a $end
$var wire 1 5 y $end
$upscope $end
$scope module or1 $end
$var wire 1 4 a $end
$var wire 1 3 b $end
$var wire 1 ! y $end
$upscope $end
$upscope $end
$upscope $end
$upscope $end
$enddefinitions $end
$comment Show the parameter values. $end
$dumpall
$end
#0
$dumpvars
15
04
03
02
11
10
0/
0.
1-
0,
0+
0*
0)
1(
b0 '
b0 &
1%
1$
0#
0"
0!
$end
#10
00
0-
1/
01
1*
1.
b1 &
b1 '
#20
10
1!
1-
0/
11
13
05
0*
0.
12
b10 &
b10 '
#30
00
0-
1/
01
1*
1.
b11 &
b11 '
#40
14
1)
1,
10
1!
1-
11
03
15
1(
0*
0.
02
0/
b0 &
b0 '
0%
1"
#50
0!
04
0)
0(
0,
00
0-
01
1*
1.
b1 &
b1 '
#60
1!
13
1)
1(
1,
10
1-
11
05
0*
0.
12
b10 &
b10 '
#70
0!
03
0)
0(
0,
00
0-
01
1*
1.
b11 &
b11 '
