App/SRAM_TCAM/rtl/priority_encoder_8_to_3.v
module priority_encoder_8_to_3(
    input [7:0] a,
    output reg [2:0] y
);
always @(*) begin
    if      (a[7]) y= 3'b111;
    else if (a[6]) y= 3'b110;
    else if (a[5]) y= 3'b101;
    else if (a[4]) y= 3'b100;
    else if (a[3]) y= 3'b011;
    else if (a[2]) y= 3'b010;
    else if (a[1]) y= 3'b001;
    else           y= 3'b000;
end
endmodule

Doc/OnTap/ThucHanh/priority_encoder_8_to_3_testbench.v
`timescale 1ps/1ps
module priority_encoder_8_to_3_tb;
reg [7:0] a;
wire [2:0] y;
priority_encoder_8_to_3 ut(
    .a(a),
    .y(y)
);
initial begin
    $dumpfile("priority_encoder_8_to_3_wave.vcd");
    $dumpvars(0,priority_encoder_8_to_3_tb);
end
initial begin
    a=8'b00000000;
    #10;
    a=8'b00000001;
    #10;
    a=8'b00000010;
    #10;
    a=8'b00000011;
    #10;
    a=8'b00000100;
    #10;
    a=8'b00000101;
    #10;
    a=8'b00000110;
    #10;
    a=8'b00000111;
    #10;
    a=8'b00001000;
    #10;
    a=8'b00001001;
    #10;
    a=8'b00001010;
    #10;
    a=8'b00001011;
    #10;
    a=8'b00001100;
    #10;
    a=8'b00001101;  
    #10;
    a=8'b00001110;
    #10;
    a=8'b00001111;
    #10;
    a=8'b00010000;
    #10;
    a=8'b00010001;
    #10;
    a=8'b00010010;
    #10;
    a=8'b00010011;
    #10;        
    a=8'b00010100;
    #10;
    a=8'b00010101;
    #10;
    a=8'b00010110;
    #10;
    a=8'b00010111;
    #10;
    a=8'b00011000;
    #10;
    a=8'b00011001;
    #10;
    a=8'b00011010;
    #10;
    a=8'b00011011;
    #10;
    a=8'b00011100;
    #10;
    a=8'b00011101;
    #10;
    a=8'b00011110;
    #10;
    a=8'b00011111;
    #10;
    a=8'b00100000;
    #10;
    a=8'b00100001;
    #10;
    a=8'b00100010;

    #10;

    a=8'b00100011;
    #10;
    a=8'b00100100;
    #10;
    a=8'b00100101;
    #10;
    a=8'b00100110;
    #10;
    a=8'b00100111;
    #10;
    a=8'b00101000;
    #10;
    a=8'b00101001;
    #10;
    a=8'b00101010;
    #10;
    a=8'b00101011;
    #10;
    a=8'b00101100;
    #10;
    a=8'b00101101;
    #10;
    a=8'b00101110;
    #10;
    a=8'b00101111;
    #10;
    a=8'b00110000;
    #10;
    a=8'b00110001;
    #10;
    a=8'b00110010;
    #10;
    a=8'b00110011;
    #10;
    a=8'b00110100;
    #10;
    a=8'b00110101;
    #10;
    a=8'b00110110;
    #10;
    a=8'b00110111;
    #10;
    a=8'b00111000;
    #10;
    a=8'b00111001;
    #10;
    a=8'b00111010;
    #10;
    a=8'b00111011;
    #10;
    a=8'b00111100;

    #10;
    a=8'b00111101;
    #10;
    a=8'b00111110;
    #10;
    a=8'b00111111;
    #10;
    a=8'b01000000;
    #10;
    a=8'b01000001;
    #10;
    a=8'b01000010;
    #10;
    a=8'b01000011;
    #10;
    a=8'b01000100;
    #10;
    a=8'b01000101;
    #10;
    a=8'b01000110;
    #10;
    a=8'b01000111;
    #10;
    a=8'b01001000;
    #10;
    a=8'b01001001;
    #10;
    a=8'b01001010;
    #10;
    a=8'b01001011;
    #10;
    a=8'b01001100;
    #10;
    a=8'b01001101;
    #10;
    a=8'b01001110;
    #10;
    a=8'b01001111;
    #10;
    a=8'b01010000;
    #10;
    a=8'b01010001;
    #10;
    a=8'b01010010;
    #10;
    a=8'b01010011;
    #10;
    a=8'b01010100;
    #10;
    a=8'b01010101;
    #10;
    a=8'b01010110;
    #10;
    a=8'b01010111;
    #10;
    a=8'b01011000;
    #10;
    a=8'b01011001;
    #10;
    a=8'b01011010;
    #10;
    a=8'b01011011;
    #10;
    a=8'b01011100;
    #10;
    a=8'b01011101;
    #10;
    a=8'b01011110;
    #10;
    a=8'b01011111;
    #10;
    a=8'b01100000;
    #10;
    a=8'b01100001;
    #10;
    a=8'b01100010;
    #10;
    a=8'b01100011;
    #10;
    a=8'b01100100;
    #10;
    a=8'b01100101;
    #10;
    a=8'b01100110;
    #10;
    a=8'b01100111;
    #10;
    a=8'b01101000;
    #10;
    a=8'b01101001;
    #10;
    a=8'b01101010;
    #10;
    a=8'b01101011;
    #10;
    a=8'b01101100;
    #10;
    a=8'b01101101;
    #10;
    a=8'b01101110;
    #10;

    a=8'b01101111;
    #10;

    a=8'b01110000;

    #10;
    a=8'b01110001;
    #10;
    a=8'b01110010;
    #10;
    a=8'b01110011;
    #10;
    a=8'b01110100;
    #10;
    a=8'b01110101;
    #10;
    a=8'b01110110;
    #10;

    a=8'b01110111;

    #10;
    a=8'b01111000;
    #10;
    a=8'b01111001;
    #10;
    a=8'b01111010;
    #10;
    a=8'b01111011;
    #10;
    a=8'b01111100;
    #10;
    a=8'b01111101;
    #10;
    a=8'b01111110;
    #10;
    a=8'b01111111;
    #10;
    a=8'b10000000;
    #10;
    a=8'b10000001;
    #10;
    a=8'b10000010;
    #10;
    a=8'b10000011;
    #10;
    a=8'b10000100;
    #10;
    a=8'b10000101;
    #10;

    a=8'b10000110;
    #10;

    a=8'b10000111;

    #10;
    a=8'b10001000;
    #10;
    a=8'b10001001;
    #10;

    a=8'b10001010;
    #10;
    a=8'b10001011;
    #10;
    a=8'b10001100;
    #10;
    a=8'b10001101;

    #10;
    a=8'b10001110;
    #10;

    a=8'b10001111;
    #10;
    a=8'b10010000;
    #10;
    a=8'b10010001;
    #10;
    a=8'b10010010;
    #10;
    a=8'b10010011;
    #10;
    a=8'b10010100;
    #10;
    a=8'b10010101;
    #10;
    a=8'b10010110;
    #10;
    a=8'b10010111;
    #10;
    a=8'b10011000;
    #10;
    a=8'b10011001;
    #10;
    a=8'b10011010;
    #10;
    a=8'b10011011;
    #10;
    a=8'b10011100;
    #10;
    a=8'b10011101;
    #10;
    a=8'b10011110;
    #10;
    a=8'b10011111;
    #10;
    a=8'b10100000;
    #10;
    a=8'b10100001;
    #10;
    a=8'b10100010;
    #10;

    a=8'b10100011;
    #10;

    a=8'b10100100;
    #10;

    a=8'b10100101;
    #10;

    a=8'b10100110;
    #10;
    a=8'b10100111;
    #10;

    a=8'b10101000;
    #10;
    a=8'b10101001;
    #10;
    a=8'b10101010;
    #10;
    a=8'b10101011;
    #10;
    a=8'b10101100;
    #10;
    a=8'b10101101;
    #10;
    a=8'b10101110;
    #10;
    a=8'b10101111;
    #10;
    a=8'b10110000;
    #10;
    a=8'b10110001;
    #10;
    a=8'b10110010;
    #10;
    a=8'b10110011;
    #10;
    a=8'b10110100;
    #10;
    a=8'b10110101;
    #10;
    a=8'b10110110;
    #10;

    a=8'b10110111;
    #10;

    a=8'b10111000;
    #10;
    a=8'b10111001;
    #10;

    a=8'b10111010;

    #10;
    a=8'b10111011;
    #10;
    a=8'b10111100;
    #10;
    a=8'b10111101;
    #10;
    a=8'b10111110;
    #10;
    a=8'b10111111;
    #10;
    a=8'b11000000;
    #10;
    a=8'b11000001;
    #10;
    a=8'b11000010;
    #10;
    a=8'b11000011;
    #10;
    a=8'b11000100;
    #10;
    a=8'b11000101;
    #10;
    a=8'b11000110;
    #10;
    a=8'b11000111;
    #10;
    a=8'b11001000;
    #10;
    a=8'b11001001;
    #10;
    a=8'b11001010;
    #10;
    a=8'b11001011;
    #10;
    a=8'b11001100;
    #10;
    a=8'b11001101;
    #10;

    a=8'b11001110;
    #10;

    a=8'b11001111;
    #10;
    a=8'b11010000;


    #10;
    a=8'b11010001;

    #10;

    a=8'b11010010;
    #10;
    a=8'b11010011;
    #10;
    a=8'b11010100;
    #10;
    a=8'b11010101;
    #10;
    a=8'b11010110;
    #10;
    a=8'b11010111;
    #10;
    a=8'b11011000;
    #10;
    a=8'b11011001;
    #10;
    a=8'b11011010;
    #10;
    a=8'b11011011;
    #10;
    a=8'b11011100;
    #10;
    a=8'b11011101;
    #10;



    a=8'b11011110;
    #10;



    a=8'b11011111;
    #10;

    a=8'b11100000;
    #10;
    a=8'b11100001;
    #10;
    a=8'b11100010;
    #10;
    a=8'b11100011;
    #10;
    a=8'b11100100;
    #10;
    a=8'b11100101;
    #10;
    a=8'b11100110;
    #10;
    a=8'b11100111;
    #10;
    a=8'b11101000;
    #10;   
    a=8'b11101001;
    #10;
    a=8'b11101010;
    #10;
    a=8'b11101011;
    #10;
    a=8'b11101100;
    #10;
    a=8'b11101101;
    #10;
    a=8'b11101110;
    #10;
    a=8'b11101111;
    #10;
    a=8'b11110000;
    #10;
    a=8'b11110001;
    #10;
    a=8'b11110010;
    #10;
    a=8'b11110011;
    #10;
    a=8'b11110100;
    #10;
    a=8'b11110101;
    #10;
    a=8'b11110110;
    #10;
    a=8'b11110111;
    #10;
    a=8'b11111000;
    #10;
    a=8'b11111001;
    #10;
    a=8'b11111010;
    #10;
    a=8'b11111011;
    #10;
    a=8'b11111100;
    #10;
    a=8'b11111101;
    #10;
    a=8'b11111110;
    #10;
    a=8'b11111111;
    #10;
    $finish;
end

initial begin
    $monitor("time=%0t a=%b y=%b"
        ,$time,a,y);
end
endmodule

Doc/OnTap/ThucHanh/priority_encoder_8_to_3_wave.vcd
$date
	Tue Jul  7 20:33:13 2026
$end
$version
	Icarus Verilog
$end
$timescale
	1ps
$end
$scope module priority_encoder_8_to_3_tb $end
$var wire 3 ! y [2:0] $end
$var reg 8 " a [7:0] $end
$scope module ut $end
$var wire 8 # a [7:0] $end
$var reg 3 $ y [2:0] $end
$upscope $end
$upscope $end
$enddefinitions $end
$comment Show the parameter values. $end
$dumpall
$end
#0
$dumpvars
b0 $
b0 #
b0 "
b0 !
$end
#10
b1 "
b1 #
#20
b1 !
b1 $
b10 "
b10 #
#30
b11 "
b11 #
#40
b10 !
b10 $
b100 "
b100 #
#50
b101 "
b101 #
#60
b110 "
b110 #
#70
b111 "
b111 #
#80
b11 !
b11 $
b1000 "
b1000 #
#90
b1001 "
b1001 #
#100
b1010 "
b1010 #
#110
b1011 "
b1011 #
#120
b1100 "
b1100 #
#130
b1101 "
b1101 #
#140
b1110 "
b1110 #
#150
b1111 "
b1111 #
#160
b100 !
b100 $
b10000 "
b10000 #
#170
b10001 "
b10001 #
#180
b10010 "
b10010 #
#190
b10011 "
b10011 #
#200
b10100 "
b10100 #
#210
b10101 "
b10101 #
#220
b10110 "
b10110 #
#230
b10111 "
b10111 #
#240
b11000 "
b11000 #
#250
b11001 "
b11001 #
#260
b11010 "
b11010 #
#270
b11011 "
b11011 #
#280
b11100 "
b11100 #
#290
b11101 "
b11101 #
#300
b11110 "
b11110 #
#310
b11111 "
b11111 #
#320
b101 !
b101 $
b100000 "
b100000 #
#330
b100001 "
b100001 #
#340
b100010 "
b100010 #
#350
b100011 "
b100011 #
#360
b100100 "
b100100 #
#370
b100101 "
b100101 #
#380
b100110 "
b100110 #
#390
b100111 "
b100111 #
#400
b101000 "
b101000 #
#410
b101001 "
b101001 #
#420
b101010 "
b101010 #
#430
b101011 "
b101011 #
#440
b101100 "
b101100 #
#450
b101101 "
b101101 #
#460
b101110 "
b101110 #
#470
b101111 "
b101111 #
#480
b110000 "
b110000 #
#490
b110001 "
b110001 #
#500
b110010 "
b110010 #
#510
b110011 "
b110011 #
#520
b110100 "
b110100 #
#530
b110101 "
b110101 #
#540
b110110 "
b110110 #
#550
b110111 "
b110111 #
#560
b111000 "
b111000 #
#570
b111001 "
b111001 #
#580
b111010 "
b111010 #
#590
b111011 "
b111011 #
#600
b111100 "
b111100 #
#610
b111101 "
b111101 #
#620
b111110 "
b111110 #
#630
b111111 "
b111111 #
#640
b110 !
b110 $
b1000000 "
b1000000 #
#650
b1000001 "
b1000001 #
#660
b1000010 "
b1000010 #
#670
b1000011 "
b1000011 #
#680
b1000100 "
b1000100 #
#690
b1000101 "
b1000101 #
#700
b1000110 "
b1000110 #
#710
b1000111 "
b1000111 #
#720
b1001000 "
b1001000 #
#730
b1001001 "
b1001001 #
#740
b1001010 "
b1001010 #
#750
b1001011 "
b1001011 #
#760
b1001100 "
b1001100 #
#770
b1001101 "
b1001101 #
#780
b1001110 "
b1001110 #
#790
b1001111 "
b1001111 #
#800
b1010000 "
b1010000 #
#810
b1010001 "
b1010001 #
#820
b1010010 "
b1010010 #
#830
b1010011 "
b1010011 #
#840
b1010100 "
b1010100 #
#850
b1010101 "
b1010101 #
#860
b1010110 "
b1010110 #
#870
b1010111 "
b1010111 #
#880
b1011000 "
b1011000 #
#890
b1011001 "
b1011001 #
#900
b1011010 "
b1011010 #
#910
b1011011 "
b1011011 #
#920
b1011100 "
b1011100 #
#930
b1011101 "
b1011101 #
#940
b1011110 "
b1011110 #
#950
b1011111 "
b1011111 #
#960
b1100000 "
b1100000 #
#970
b1100001 "
b1100001 #
#980
b1100010 "
b1100010 #
#990
b1100011 "
b1100011 #
#1000
b1100100 "
b1100100 #
#1010
b1100101 "
b1100101 #
#1020
b1100110 "
b1100110 #
#1030
b1100111 "
b1100111 #
#1040
b1101000 "
b1101000 #
#1050
b1101001 "
b1101001 #
#1060
b1101010 "
b1101010 #
#1070
b1101011 "
b1101011 #
#1080
b1101100 "
b1101100 #
#1090
b1101101 "
b1101101 #
#1100
b1101110 "
b1101110 #
#1110
b1101111 "
b1101111 #
#1120
b1110000 "
b1110000 #
#1130
b1110001 "
b1110001 #
#1140
b1110010 "
b1110010 #
#1150
b1110011 "
b1110011 #
#1160
b1110100 "
b1110100 #
#1170
b1110101 "
b1110101 #
#1180
b1110110 "
b1110110 #
#1190
b1110111 "
b1110111 #
#1200
b1111000 "
b1111000 #
#1210
b1111001 "
b1111001 #
#1220
b1111010 "
b1111010 #
#1230
b1111011 "
b1111011 #
#1240
b1111100 "
b1111100 #
#1250
b1111101 "
b1111101 #
#1260
b1111110 "
b1111110 #
#1270
b1111111 "
b1111111 #
#1280
b111 !
b111 $
b10000000 "
b10000000 #
#1290
b10000001 "
b10000001 #
#1300
b10000010 "
b10000010 #
#1310
b10000011 "
b10000011 #
#1320
b10000100 "
b10000100 #
#1330
b10000101 "
b10000101 #
#1340
b10000110 "
b10000110 #
#1350
b10000111 "
b10000111 #
#1360
b10001000 "
b10001000 #
#1370
b10001001 "
b10001001 #
#1380
b10001010 "
b10001010 #
#1390
b10001011 "
b10001011 #
#1400
b10001100 "
b10001100 #
#1410
b10001101 "
b10001101 #
#1420
b10001110 "
b10001110 #
#1430
b10001111 "
b10001111 #
#1440
b10010000 "
b10010000 #
#1450
b10010001 "
b10010001 #
#1460
b10010010 "
b10010010 #
#1470
b10010011 "
b10010011 #
#1480
b10010100 "
b10010100 #
#1490
b10010101 "
b10010101 #
#1500
b10010110 "
b10010110 #
#1510
b10010111 "
b10010111 #
#1520
b10011000 "
b10011000 #
#1530
b10011001 "
b10011001 #
#1540
b10011010 "
b10011010 #
#1550
b10011011 "
b10011011 #
#1560
b10011100 "
b10011100 #
#1570
b10011101 "
b10011101 #
#1580
b10011110 "
b10011110 #
#1590
b10011111 "
b10011111 #
#1600
b10100000 "
b10100000 #
#1610
b10100001 "
b10100001 #
#1620
b10100010 "
b10100010 #
#1630
b10100011 "
b10100011 #
#1640
b10100100 "
b10100100 #
#1650
b10100101 "
b10100101 #
#1660
b10100110 "
b10100110 #
#1670
b10100111 "
b10100111 #
#1680
b10101000 "
b10101000 #
#1690
b10101001 "
b10101001 #
#1700
b10101010 "
b10101010 #
#1710
b10101011 "
b10101011 #
#1720
b10101100 "
b10101100 #
#1730
b10101101 "
b10101101 #
#1740
b10101110 "
b10101110 #
#1750
b10101111 "
b10101111 #
#1760
b10110000 "
b10110000 #
#1770
b10110001 "
b10110001 #
#1780
b10110010 "
b10110010 #
#1790
b10110011 "
b10110011 #
#1800
b10110100 "
b10110100 #
#1810
b10110101 "
b10110101 #
#1820
b10110110 "
b10110110 #
#1830
b10110111 "
b10110111 #
#1840
b10111000 "
b10111000 #
#1850
b10111001 "
b10111001 #
#1860
b10111010 "
b10111010 #
#1870
b10111011 "
b10111011 #
#1880
b10111100 "
b10111100 #
#1890
b10111101 "
b10111101 #
#1900
b10111110 "
b10111110 #
#1910
b10111111 "
b10111111 #
#1920
b11000000 "
b11000000 #
#1930
b11000001 "
b11000001 #
#1940
b11000010 "
b11000010 #
#1950
b11000011 "
b11000011 #
#1960
b11000100 "
b11000100 #
#1970
b11000101 "
b11000101 #
#1980
b11000110 "
b11000110 #
#1990
b11000111 "
b11000111 #
#2000
b11001000 "
b11001000 #
#2010
b11001001 "
b11001001 #
#2020
b11001010 "
b11001010 #
#2030
b11001011 "
b11001011 #
#2040
b11001100 "
b11001100 #
#2050
b11001101 "
b11001101 #
#2060
b11001110 "
b11001110 #
#2070
b11001111 "
b11001111 #
#2080
b11010000 "
b11010000 #
#2090
b11010001 "
b11010001 #
#2100
b11010010 "
b11010010 #
#2110
b11010011 "
b11010011 #
#2120
b11010100 "
b11010100 #
#2130
b11010101 "
b11010101 #
#2140
b11010110 "
b11010110 #
#2150
b11010111 "
b11010111 #
#2160
b11011000 "
b11011000 #
#2170
b11011001 "
b11011001 #
#2180
b11011010 "
b11011010 #
#2190
b11011011 "
b11011011 #
#2200
b11011100 "
b11011100 #
#2210
b11011101 "
b11011101 #
#2220
b11011110 "
b11011110 #
#2230
b11011111 "
b11011111 #
#2240
b11100000 "
b11100000 #
#2250
b11100001 "
b11100001 #
#2260
b11100010 "
b11100010 #
#2270
b11100011 "
b11100011 #
#2280
b11100100 "
b11100100 #
#2290
b11100101 "
b11100101 #
#2300
b11100110 "
b11100110 #
#2310
b11100111 "
b11100111 #
#2320
b11101000 "
b11101000 #
#2330
b11101001 "
b11101001 #
#2340
b11101010 "
b11101010 #
#2350
b11101011 "
b11101011 #
#2360
b11101100 "
b11101100 #
#2370
b11101101 "
b11101101 #
#2380
b11101110 "
b11101110 #
#2390
b11101111 "
b11101111 #
#2400
b11110000 "
b11110000 #
#2410
b11110001 "
b11110001 #
#2420
b11110010 "
b11110010 #
#2430
b11110011 "
b11110011 #
#2440
b11110100 "
b11110100 #
#2450
b11110101 "
b11110101 #
#2460
b11110110 "
b11110110 #
#2470
b11110111 "
b11110111 #
#2480
b11111000 "
b11111000 #
#2490
b11111001 "
b11111001 #
#2500
b11111010 "
b11111010 #
#2510
b11111011 "
b11111011 #
#2520
b11111100 "
b11111100 #
#2530
b11111101 "
b11111101 #
#2540
b11111110 "
b11111110 #
#2550
b11111111 "
b11111111 #
